tokema/__init__.py
tokema/eof.py
tokema/grammar.py
tokema/parsing.py
tokema/table.py
tokema/text.py
tokema/utils.py
tokema-0.0.2.dist-info/LICENCE
tokema-0.0.2.dist-info/METADATA
tokema-0.0.2.dist-info/WHEEL
tokema-0.0.2.dist-info/top_level.txt
tokema-0.0.2.dist-info/RECORD
